MANIFEST.in
README.md
setup.cfg
setup.py
protocol_parser/__init__.py
protocol_parser/protocol_parser.py
protocol_parser.egg-info/PKG-INFO
protocol_parser.egg-info/SOURCES.txt
protocol_parser.egg-info/dependency_links.txt
protocol_parser.egg-info/not-zip-safe
protocol_parser.egg-info/top_level.txt
protocol_parser/parsing_elements/__init__.py
protocol_parser/parsing_elements/condition_element.py
protocol_parser/parsing_elements/const_element.py
protocol_parser/parsing_elements/length_variable_element.py
protocol_parser/parsing_elements/sized_group_element.py
protocol_parser/parsing_elements/string_parser.py
protocol_parser/parsing_elements/switch_element.py
protocol_parser/parsing_elements/timed_loop_element.py
protocol_parser/parsing_elements/unsized_group_element.py
protocol_parser/parsing_elements/untimed_loop_element.py
protocol_parser/parsing_elements/variable_element.py
protocol_parser/parsing_matches/__init__.py
protocol_parser/parsing_matches/condition_match.py
protocol_parser/parsing_matches/const_match.py
protocol_parser/parsing_matches/length_variable_match.py
protocol_parser/parsing_matches/parsing_exceptions.py
protocol_parser/parsing_matches/sized_group_match.py
protocol_parser/parsing_matches/switch_match.py
protocol_parser/parsing_matches/timed_loop_match.py
protocol_parser/parsing_matches/unsized_group_match.py
protocol_parser/parsing_matches/untimed_group_match.py
protocol_parser/parsing_matches/variable_match.py
tests/test_edge_cases.py
tests/test_ip_example.py
tests/test_sanity.py
tests/test_string_parser.py