Metadata-Version: 1.1
Name: protocol-parser
Version: 0.1
Summary: package for parsing data easily
Home-page: https://github.com/matan1008/protocol_parser
Author: Matan Perelman
Author-email: matan1008@gmail.com
License: MIT
Download-URL: https://github.com/matan1008/protocol_parser/tarball/0.1
Platform: UNKNOWN
